[
	{
		"count": 1,
		"filter": "g",
		"exptime": 812.000000,
		"RA": 121.679750,
		"dec": -24.030000,
		"object": "S240422ed 3014397",
		"program": "GW-MMADS",
		"expType": "object",
		"note": "None",
		"comment": "2023B-851374",
		"wait": "False",
		"proposer": "Andreoni Palmese",
		"propid": "2023B-851374"
	},
	{
		"count": 1,
		"filter": "g",
		"exptime": 706.000000,
		"RA": 121.151750,
		"dec": -22.459000,
		"object": "S240422ed 3014380",
		"program": "GW-MMADS",
		"expType": "object",
		"note": "None",
		"comment": "2023B-851374",
		"wait": "False",
		"proposer": "Andreoni Palmese",
		"propid": "2023B-851374"
	},
	{
		"count": 1,
		"filter": "g",
		"exptime": 706.000000,
		"RA": 120.776750,
		"dec": -26.731000,
		"object": "S240422ed 3014414",
		"program": "GW-MMADS",
		"expType": "object",
		"note": "None",
		"comment": "2023B-851374",
		"wait": "False",
		"proposer": "Andreoni Palmese",
		"propid": "2023B-851374"
	},
	{
		"count": 1,
		"filter": "g",
		"exptime": 600.000000,
		"RA": 119.847750,
		"dec": -29.431000,
		"object": "S240422ed 3014433",
		"program": "GW-MMADS",
		"expType": "object",
		"note": "None",
		"comment": "2023B-851374",
		"wait": "False",
		"proposer": "Andreoni Palmese",
		"propid": "2023B-851374"
	},
	{
		"count": 1,
		"filter": "g",
		"exptime": 600.000000,
		"RA": 119.307750,
		"dec": -27.829000,
		"object": "S240422ed 3014413",
		"program": "GW-MMADS",
		"expType": "object",
		"note": "None",
		"comment": "2023B-851374",
		"wait": "False",
		"proposer": "Andreoni Palmese",
		"propid": "2023B-851374"
	},
	{
		"count": 1,
		"filter": "g",
		"exptime": 600.000000,
		"RA": 120.242750,
		"dec": -25.145000,
		"object": "S240422ed 3014396",
		"program": "GW-MMADS",
		"expType": "object",
		"note": "None",
		"comment": "2023B-851374",
		"wait": "False",
		"proposer": "Andreoni Palmese",
		"propid": "2023B-851374"
	},
	{
		"count": 1,
		"filter": "g",
		"exptime": 600.000000,
		"RA": 122.562750,
		"dec": -21.326000,
		"object": "S240422ed 3014381",
		"program": "GW-MMADS",
		"expType": "object",
		"note": "None",
		"comment": "2023B-851374",
		"wait": "False",
		"proposer": "Andreoni Palmese",
		"propid": "2023B-851374"
	},
	{
		"count": 1,
		"filter": "g",
		"exptime": 494.000000,
		"RA": 121.325750,
		"dec": -28.324000,
		"object": "S240422ed 3014434",
		"program": "GW-MMADS",
		"expType": "object",
		"note": "None",
		"comment": "2023B-851374",
		"wait": "False",
		"proposer": "Andreoni Palmese",
		"propid": "2023B-851374"
	},
	{
		"count": 1,
		"filter": "g",
		"exptime": 494.000000,
		"RA": 123.096750,
		"dec": -22.885000,
		"object": "S240422ed 3014398",
		"program": "GW-MMADS",
		"expType": "object",
		"note": "None",
		"comment": "2023B-851374",
		"wait": "False",
		"proposer": "Andreoni Palmese",
		"propid": "2023B-851374"
	},
	{
		"count": 1,
		"filter": "g",
		"exptime": 494.000000,
		"RA": 119.723750,
		"dec": -23.562000,
		"object": "S240422ed 3014379",
		"program": "GW-MMADS",
		"expType": "object",
		"note": "None",
		"comment": "2023B-851374",
		"wait": "False",
		"proposer": "Andreoni Palmese",
		"propid": "2023B-851374"
	},
	{
		"count": 1,
		"filter": "g",
		"exptime": 494.000000,
		"RA": 118.784750,
		"dec": -26.231000,
		"object": "S240422ed 3014395",
		"program": "GW-MMADS",
		"expType": "object",
		"note": "None",
		"comment": "2023B-851374",
		"wait": "False",
		"proposer": "Andreoni Palmese",
		"propid": "2023B-851374"
	},
	{
		"count": 1,
		"filter": "g",
		"exptime": 494.000000,
		"RA": 123.955750,
		"dec": -20.162000,
		"object": "S240422ed 3014382",
		"program": "GW-MMADS",
		"expType": "object",
		"note": "None",
		"comment": "2023B-851374",
		"wait": "False",
		"proposer": "Andreoni Palmese",
		"propid": "2023B-851374"
	},
	{
		"count": 1,
		"filter": "g",
		"exptime": 388.000000,
		"RA": 123.427750,
		"dec": -18.619000,
		"object": "S240422ed 3014366",
		"program": "GW-MMADS",
		"expType": "object",
		"note": "None",
		"comment": "2023B-851374",
		"wait": "False",
		"proposer": "Andreoni Palmese",
		"propid": "2023B-851374"
	},
	{
		"count": 1,
		"filter": "g",
		"exptime": 388.000000,
		"RA": 122.039750,
		"dec": -19.772000,
		"object": "S240422ed 3014365",
		"program": "GW-MMADS",
		"expType": "object",
		"note": "None",
		"comment": "2023B-851374",
		"wait": "False",
		"proposer": "Andreoni Palmese",
		"propid": "2023B-851374"
	},
	{
		"count": 1,
		"filter": "g",
		"exptime": 70.000000,
		"RA": 123.644750,
		"dec": -24.450000,
		"object": "S240422ed 3014416",
		"program": "GW-MMADS",
		"expType": "object",
		"note": "None",
		"comment": "2023B-851374",
		"wait": "False",
		"proposer": "Andreoni Palmese",
		"propid": "2023B-851374"
	},
	{
		"count": 1,
		"filter": "g",
		"exptime": 388.000000,
		"RA": 117.815750,
		"dec": -28.899000,
		"object": "S240422ed 3014412",
		"program": "GW-MMADS",
		"expType": "object",
		"note": "None",
		"comment": "2023B-851374",
		"wait": "False",
		"proposer": "Andreoni Palmese",
		"propid": "2023B-851374"
	},
	{
		"count": 1,
		"filter": "g",
		"exptime": 388.000000,
		"RA": 121.892750,
		"dec": -29.923000,
		"object": "S240422ed 3014455",
		"program": "GW-MMADS",
		"expType": "object",
		"note": "None",
		"comment": "2023B-851374",
		"wait": "False",
		"proposer": "Andreoni Palmese",
		"propid": "2023B-851374"
	},
	{
		"count": 1,
		"filter": "g",
		"exptime": 282.000000,
		"RA": 123.644750,
		"dec": -24.450000,
		"object": "S240422ed 3014416",
		"program": "GW-MMADS",
		"expType": "object",
		"note": "None",
		"comment": "2023B-851374",
		"wait": "False",
		"proposer": "Andreoni Palmese",
		"propid": "2023B-851374"
	},
	{
		"count": 1,
		"filter": "g",
		"exptime": 388.000000,
		"RA": 122.778750,
		"dec": -27.187000,
		"object": "S240422ed 3014435",
		"program": "GW-MMADS",
		"expType": "object",
		"note": "None",
		"comment": "2023B-851374",
		"wait": "False",
		"proposer": "Andreoni Palmese",
		"propid": "2023B-851374"
	},
	{
		"count": 1,
		"filter": "g",
		"exptime": 388.000000,
		"RA": 122.221750,
		"dec": -25.605000,
		"object": "S240422ed 3014415",
		"program": "GW-MMADS",
		"expType": "object",
		"note": "None",
		"comment": "2023B-851374",
		"wait": "False",
		"proposer": "Andreoni Palmese",
		"propid": "2023B-851374"
	},
	{
		"count": 1,
		"filter": "g",
		"exptime": 388.000000,
		"RA": 118.887750,
		"dec": -32.128000,
		"object": "S240422ed 3012341",
		"program": "GW-MMADS",
		"expType": "object",
		"note": "None",
		"comment": "2023B-851374",
		"wait": "False",
		"proposer": "Andreoni Palmese",
		"propid": "2023B-851374"
	},
	{
		"count": 1,
		"filter": "g",
		"exptime": 70.000000,
		"RA": 118.276750,
		"dec": -24.637000,
		"object": "S240422ed 3014378",
		"program": "GW-MMADS",
		"expType": "object",
		"note": "None",
		"comment": "2023B-851374",
		"wait": "False",
		"proposer": "Andreoni Palmese",
		"propid": "2023B-851374"
	},
	{
		"count": 1,
		"filter": "g",
		"exptime": 282.000000,
		"RA": 121.527750,
		"dec": -18.220000,
		"object": "S240422ed 3014350",
		"program": "GW-MMADS",
		"expType": "object",
		"note": "None",
		"comment": "2023B-851374",
		"wait": "False",
		"proposer": "Andreoni Palmese",
		"propid": "2023B-851374"
	},
	{
		"count": 1,
		"filter": "g",
		"exptime": 176.000000,
		"RA": 118.276750,
		"dec": -24.637000,
		"object": "S240422ed 3014378",
		"program": "GW-MMADS",
		"expType": "object",
		"note": "None",
		"comment": "2023B-851374",
		"wait": "False",
		"proposer": "Andreoni Palmese",
		"propid": "2023B-851374"
	},
	{
		"count": 1,
		"filter": "g",
		"exptime": 282.000000,
		"RA": 119.216750,
		"dec": -21.981000,
		"object": "S240422ed 3014363",
		"program": "GW-MMADS",
		"expType": "object",
		"note": "None",
		"comment": "2023B-851374",
		"wait": "False",
		"proposer": "Andreoni Palmese",
		"propid": "2023B-851374"
	},
	{
		"count": 1,
		"filter": "g",
		"exptime": 282.000000,
		"RA": 125.329750,
		"dec": -18.962000,
		"object": "S240422ed 3014383",
		"program": "GW-MMADS",
		"expType": "object",
		"note": "None",
		"comment": "2023B-851374",
		"wait": "False",
		"proposer": "Andreoni Palmese",
		"propid": "2023B-851374"
	},
	{
		"count": 1,
		"filter": "g",
		"exptime": 282.000000,
		"RA": 120.636750,
		"dec": -20.891000,
		"object": "S240422ed 3014364",
		"program": "GW-MMADS",
		"expType": "object",
		"note": "None",
		"comment": "2023B-851374",
		"wait": "False",
		"proposer": "Andreoni Palmese",
		"propid": "2023B-851374"
	},
	{
		"count": 1,
		"filter": "g",
		"exptime": 282.000000,
		"RA": 122.909750,
		"dec": -17.081000,
		"object": "S240422ed 3014351",
		"program": "GW-MMADS",
		"expType": "object",
		"note": "None",
		"comment": "2023B-851374",
		"wait": "False",
		"proposer": "Andreoni Palmese",
		"propid": "2023B-851374"
	},
	{
		"count": 1,
		"filter": "g",
		"exptime": 282.000000,
		"RA": 125.872750,
		"dec": -20.499000,
		"object": "S240422ed 3014400",
		"program": "GW-MMADS",
		"expType": "object",
		"note": "None",
		"comment": "2023B-851374",
		"wait": "False",
		"proposer": "Andreoni Palmese",
		"propid": "2023B-851374"
	},
	{
		"count": 1,
		"filter": "g",
		"exptime": 282.000000,
		"RA": 120.131750,
		"dec": -19.324000,
		"object": "S240422ed 3014349",
		"program": "GW-MMADS",
		"expType": "object",
		"note": "None",
		"comment": "2023B-851374",
		"wait": "False",
		"proposer": "Andreoni Palmese",
		"propid": "2023B-851374"
	},
	{
		"count": 1,
		"filter": "g",
		"exptime": 282.000000,
		"RA": 127.229750,
		"dec": -19.253000,
		"object": "S240422ed 3014401",
		"program": "GW-MMADS",
		"expType": "object",
		"note": "None",
		"comment": "2023B-851374",
		"wait": "False",
		"proposer": "Andreoni Palmese",
		"propid": "2023B-851374"
	},
	{
		"count": 1,
		"filter": "g",
		"exptime": 282.000000,
		"RA": 126.151750,
		"dec": -16.201000,
		"object": "S240422ed 3014368",
		"program": "GW-MMADS",
		"expType": "object",
		"note": "None",
		"comment": "2023B-851374",
		"wait": "False",
		"proposer": "Andreoni Palmese",
		"propid": "2023B-851374"
	},
	{
		"count": 1,
		"filter": "g",
		"exptime": 282.000000,
		"RA": 124.798750,
		"dec": -17.430000,
		"object": "S240422ed 3014367",
		"program": "GW-MMADS",
		"expType": "object",
		"note": "None",
		"comment": "2023B-851374",
		"wait": "False",
		"proposer": "Andreoni Palmese",
		"propid": "2023B-851374"
	},
	{
		"count": 1,
		"filter": "g",
		"exptime": 70.000000,
		"RA": 125.046750,
		"dec": -23.263000,
		"object": "S240422ed 3014417",
		"program": "GW-MMADS",
		"expType": "object",
		"note": "None",
		"comment": "2023B-851374",
		"wait": "False",
		"proposer": "Andreoni Palmese",
		"propid": "2023B-851374"
	},
	{
		"count": 1,
		"filter": "g",
		"exptime": 70.000000,
		"RA": 120.405750,
		"dec": -31.040000,
		"object": "S240422ed 3014454",
		"program": "GW-MMADS",
		"expType": "object",
		"note": "None",
		"comment": "2023B-851374",
		"wait": "False",
		"proposer": "Andreoni Palmese",
		"propid": "2023B-851374"
	},
	{
		"count": 1,
		"filter": "g",
		"exptime": 282.000000,
		"RA": 120.981750,
		"dec": -32.656000,
		"object": "S240422ed 3012364",
		"program": "GW-MMADS",
		"expType": "object",
		"note": "None",
		"comment": "2023B-851374",
		"wait": "False",
		"proposer": "Andreoni Palmese",
		"propid": "2023B-851374"
	},
	{
		"count": 1,
		"filter": "g",
		"exptime": 176.000000,
		"RA": 120.405750,
		"dec": -31.040000,
		"object": "S240422ed 3014454",
		"program": "GW-MMADS",
		"expType": "object",
		"note": "None",
		"comment": "2023B-851374",
		"wait": "False",
		"proposer": "Andreoni Palmese",
		"propid": "2023B-851374"
	},
	{
		"count": 1,
		"filter": "g",
		"exptime": 282.000000,
		"RA": 119.445750,
		"dec": -33.752000,
		"object": "S240422ed 3012363",
		"program": "GW-MMADS",
		"expType": "object",
		"note": "None",
		"comment": "2023B-851374",
		"wait": "False",
		"proposer": "Andreoni Palmese",
		"propid": "2023B-851374"
	},
	{
		"count": 1,
		"filter": "g",
		"exptime": 282.000000,
		"RA": 118.343750,
		"dec": -30.511000,
		"object": "S240422ed 3014432",
		"program": "GW-MMADS",
		"expType": "object",
		"note": "None",
		"comment": "2023B-851374",
		"wait": "False",
		"proposer": "Andreoni Palmese",
		"propid": "2023B-851374"
	},
	{
		"count": 1,
		"filter": "g",
		"exptime": 70.000000,
		"RA": 124.207750,
		"dec": -26.021000,
		"object": "S240422ed 3014436",
		"program": "GW-MMADS",
		"expType": "object",
		"note": "None",
		"comment": "2023B-851374",
		"wait": "False",
		"proposer": "Andreoni Palmese",
		"propid": "2023B-851374"
	},
	{
		"count": 1,
		"filter": "g",
		"exptime": 176.000000,
		"RA": 125.046750,
		"dec": -23.263000,
		"object": "S240422ed 3014417",
		"program": "GW-MMADS",
		"expType": "object",
		"note": "None",
		"comment": "2023B-851374",
		"wait": "False",
		"proposer": "Andreoni Palmese",
		"propid": "2023B-851374"
	},
	{
		"count": 1,
		"filter": "g",
		"exptime": 176.000000,
		"RA": 124.207750,
		"dec": -26.021000,
		"object": "S240422ed 3014436",
		"program": "GW-MMADS",
		"expType": "object",
		"note": "None",
		"comment": "2023B-851374",
		"wait": "False",
		"proposer": "Andreoni Palmese",
		"propid": "2023B-851374"
	},
	{
		"count": 1,
		"filter": "g",
		"exptime": 70.000000,
		"RA": 125.613750,
		"dec": -24.823000,
		"object": "S240422ed 3014437",
		"program": "GW-MMADS",
		"expType": "object",
		"note": "None",
		"comment": "2023B-851374",
		"wait": "False",
		"proposer": "Andreoni Palmese",
		"propid": "2023B-851374"
	},
	{
		"count": 1,
		"filter": "g",
		"exptime": 70.000000,
		"RA": 128.020750,
		"dec": -16.455000,
		"object": "S240422ed 3014385",
		"program": "GW-MMADS",
		"expType": "object",
		"note": "None",
		"comment": "2023B-851374",
		"wait": "False",
		"proposer": "Andreoni Palmese",
		"propid": "2023B-851374"
	},
	{
		"count": 1,
		"filter": "g",
		"exptime": 176.000000,
		"RA": 128.566750,
		"dec": -17.978000,
		"object": "S240422ed 3014402",
		"program": "GW-MMADS",
		"expType": "object",
		"note": "None",
		"comment": "2023B-851374",
		"wait": "False",
		"proposer": "Andreoni Palmese",
		"propid": "2023B-851374"
	},
	{
		"count": 1,
		"filter": "g",
		"exptime": 70.000000,
		"RA": 125.613750,
		"dec": -24.823000,
		"object": "S240422ed 3014437",
		"program": "GW-MMADS",
		"expType": "object",
		"note": "None",
		"comment": "2023B-851374",
		"wait": "False",
		"proposer": "Andreoni Palmese",
		"propid": "2023B-851374"
	},
	{
		"count": 1,
		"filter": "g",
		"exptime": 70.000000,
		"RA": 127.785750,
		"dec": -20.789000,
		"object": "S240422ed 3014419",
		"program": "GW-MMADS",
		"expType": "object",
		"note": "None",
		"comment": "2023B-851374",
		"wait": "False",
		"proposer": "Andreoni Palmese",
		"propid": "2023B-851374"
	},
	{
		"count": 1,
		"filter": "g",
		"exptime": 176.000000,
		"RA": 126.997750,
		"dec": -23.594000,
		"object": "S240422ed 3014438",
		"program": "GW-MMADS",
		"expType": "object",
		"note": "None",
		"comment": "2023B-851374",
		"wait": "False",
		"proposer": "Andreoni Palmese",
		"propid": "2023B-851374"
	},
	{
		"count": 1,
		"filter": "g",
		"exptime": 176.000000,
		"RA": 123.353750,
		"dec": -28.776000,
		"object": "S240422ed 3014456",
		"program": "GW-MMADS",
		"expType": "object",
		"note": "None",
		"comment": "2023B-851374",
		"wait": "False",
		"proposer": "Andreoni Palmese",
		"propid": "2023B-851374"
	},
	{
		"count": 1,
		"filter": "g",
		"exptime": 70.000000,
		"RA": 127.583750,
		"dec": -25.154000,
		"object": "S240422ed 3014459",
		"program": "GW-MMADS",
		"expType": "object",
		"note": "None",
		"comment": "2023B-851374",
		"wait": "False",
		"proposer": "Andreoni Palmese",
		"propid": "2023B-851374"
	},
	{
		"count": 1,
		"filter": "g",
		"exptime": 70.000000,
		"RA": 125.387750,
		"dec": -29.187000,
		"object": "S240422ed 3014479",
		"program": "GW-MMADS",
		"expType": "object",
		"note": "None",
		"comment": "2023B-851374",
		"wait": "False",
		"proposer": "Andreoni Palmese",
		"propid": "2023B-851374"
	},
	{
		"count": 1,
		"filter": "g",
		"exptime": 70.000000,
		"RA": 124.563750,
		"dec": -31.981000,
		"object": "S240422ed 3014497",
		"program": "GW-MMADS",
		"expType": "object",
		"note": "None",
		"comment": "2023B-851374",
		"wait": "False",
		"proposer": "Andreoni Palmese",
		"propid": "2023B-851374"
	},
	{
		"count": 1,
		"filter": "g",
		"exptime": 70.000000,
		"RA": 126.007750,
		"dec": -30.785000,
		"object": "S240422ed 3014498",
		"program": "GW-MMADS",
		"expType": "object",
		"note": "None",
		"comment": "2023B-851374",
		"wait": "False",
		"proposer": "Andreoni Palmese",
		"propid": "2023B-851374"
	},
	{
		"count": 1,
		"filter": "g",
		"exptime": 70.000000,
		"RA": 127.423750,
		"dec": -29.558000,
		"object": "S240422ed 3014499",
		"program": "GW-MMADS",
		"expType": "object",
		"note": "None",
		"comment": "2023B-851374",
		"wait": "False",
		"proposer": "Andreoni Palmese",
		"propid": "2023B-851374"
	},
	{
		"count": 1,
		"filter": "g",
		"exptime": 70.000000,
		"RA": 128.187750,
		"dec": -26.723000,
		"object": "S240422ed 3014481",
		"program": "GW-MMADS",
		"expType": "object",
		"note": "None",
		"comment": "2023B-851374",
		"wait": "False",
		"proposer": "Andreoni Palmese",
		"propid": "2023B-851374"
	},
	{
		"count": 1,
		"filter": "g",
		"exptime": 70.000000,
		"RA": 126.652750,
		"dec": -32.392000,
		"object": "S240422ed 3014514",
		"program": "GW-MMADS",
		"expType": "object",
		"note": "None",
		"comment": "2023B-851374",
		"wait": "False",
		"proposer": "Andreoni Palmese",
		"propid": "2023B-851374"
	},
	{
		"count": 1,
		"filter": "g",
		"exptime": 70.000000,
		"RA": 128.070750,
		"dec": -31.156000,
		"object": "S240422ed 3014515",
		"program": "GW-MMADS",
		"expType": "object",
		"note": "None",
		"comment": "2023B-851374",
		"wait": "False",
		"proposer": "Andreoni Palmese",
		"propid": "2023B-851374"
	}
/
